AUTHORS
CHANGELOG
LICENSE
MANIFEST.in
setup.py
django_issue_synchronisation.egg-info/PKG-INFO
django_issue_synchronisation.egg-info/SOURCES.txt
django_issue_synchronisation.egg-info/dependency_links.txt
django_issue_synchronisation.egg-info/requires.txt
django_issue_synchronisation.egg-info/top_level.txt
issues/__init__.py
issues/admin.py
issues/core.py
issues/models.py
issues/plugin.py
issues/signals.py
issues/views.py
issues/backends/__init__.py
issues/backends/github.py
issues/backends/roundup.py
issues/backends/trac.py
issues/fixtures/initial_data.json
issues/hooks/__init__.py
issues/hooks/hook.py.sample
issues/management/__init__.py
issues/management/commands/__init__.py
issues/management/commands/manage_sync.py
issues/management/commands/sync_issues.py
issues/templates/admin/issues/tracker/change_list.html
issues/tests/__init__.py
issues/tests/models.py