Metadata-Version: 1.0
Name: django-issue-synchronisation
Version: 0.1.6
Summary: Issue synchronisation for django applications
Home-page: http://django-issue-synchronisation.googlecode.com
Author: Henning Kage
Author-email: henning.kage@googlemail.com
License: GPLv3
Platform: UNKNOWN
Classifier: Development Status :: 3 - Alpha
Classifier: Framework :: Django
Classifier: License :: OSI Approved :: GNU General Public License (GPL)
Classifier: Natural Language :: English
Classifier: Operating System :: OS Independent
Classifier: Programming Language :: Python
Classifier: Topic :: Software Development :: Bug Tracking
